README.txt
setup.cfg
setup.py
docs/HISTORY.txt
docs/LICENSE.GPL
docs/LICENSE.txt
docs/MANUAL.txt
raptus/__init__.py
raptus.article.backlink.egg-info/PKG-INFO
raptus.article.backlink.egg-info/SOURCES.txt
raptus.article.backlink.egg-info/dependency_links.txt
raptus.article.backlink.egg-info/entry_points.txt
raptus.article.backlink.egg-info/namespace_packages.txt
raptus.article.backlink.egg-info/not-zip-safe
raptus.article.backlink.egg-info/requires.txt
raptus.article.backlink.egg-info/top_level.txt
raptus/article/__init__.py
raptus/article/backlink/__init__.py
raptus/article/backlink/configure.zcml
raptus/article/backlink/browser/__init__.py
raptus/article/backlink/browser/backlink.gif
raptus/article/backlink/browser/backlink.py
raptus/article/backlink/browser/configure.zcml
raptus/article/backlink/i18n/raptus.article-de.po
raptus/article/backlink/i18n/raptus.article.pot
raptus/article/backlink/profiles/default/metadata.xml
raptus/article/backlink/profiles/default/viewlets.xml