Metadata-Version: 1.0
Name: raptus.article.backlink
Version: 1.0a1
Summary: Provides a component displaying a back link using raptus.backlink
Home-page: http://raptus.com
Author: Raptus AG
Author-email: dev@raptus.com
License: GPL
Platform: UNKNOWN
Classifier: Programming Language :: Python
Classifier: Topic :: Software Development :: Libraries :: Python Modules
